{"en_example_index.md":"447b5d6d","en_guide_index.md":"39877e32","en_index.md":"92c5c0f5","example_customize_drop-effects.md":"6f9f2a1d","example_customize_handles-and-previews.md":"2d317210","example_drag-around_custom-drag-layer.md":"1c706eaf","example_drag-around_naive.md":"3a1e6ebc","example_dustbin_copy-or-move.md":"4a395670","example_dustbin_iframe.md":"3d102a3a","example_dustbin_multiple-targets.md":"e4e55e5c","example_dustbin_single-target.md":"e43ecda8","example_dustbin_stress-test.md":"b8b7e42d","example_index.md":"7aa3aee8","example_nesting_drag-sources.md":"bd38f4e2","example_nesting_drop-targets.md":"8e702a7c","example_other_native-files.md":"064d7f8c","example_other_native-html.md":"a34ab058","example_sortable_cancel-on-drop-outside.md":"a7b84941","example_sortable_simple.md":"f4c50e8d","example_sortable_stress-test.md":"0a5d1790","guide_backend_html5.md":"da220f69","guide_backend_test.md":"8888cbfd","guide_backend_touch.md":"88bb5384","guide_components_dnd-provider.md":"3e809c3d","guide_components_drag-preview-image.md":"71a2e168","guide_composition_index.md":"490521b6","guide_composition_use-drag-layer.md":"2eb5a365","guide_composition_use-drag.md":"55b9b4ff","guide_composition_use-drop.md":"49d594a4","guide_faq.md":"5fc6edde","guide_index.md":"eda6e1ab","guide_monitors_drag-layer-monitor.md":"9888a392","guide_monitors_drag-source-monitor.md":"2746f624","guide_monitors_drop-target-monitor.md":"4bffb4f4","guide_overview.md":"3fd8b169","guide_v1-to-v2.md":"2daf2213","guide_vue2.md":"fe13d297","index.md":"e5fc7eba"}
