{"en_example_index.md":"0555c1b6","en_guide_index.md":"196b7e3e","en_index.md":"d3be29de","example_customize_drop-effects.md":"2dc03eb8","example_customize_handles-and-previews.md":"804aaeda","example_drag-around_custom-drag-layer.md":"8fd80c82","example_drag-around_naive.md":"6e01992b","example_dustbin_copy-or-move.md":"4ee0336f","example_dustbin_iframe.md":"fd3d18e0","example_dustbin_multiple-targets.md":"09a5e704","example_dustbin_single-target.md":"b4a88be4","example_dustbin_stress-test.md":"902bc04c","example_index.md":"08fe1593","example_nesting_drag-sources.md":"94992c86","example_nesting_drop-targets.md":"7e3f4329","example_other_native-files.md":"db77d0a6","example_other_native-html.md":"55d18934","example_sortable_cancel-on-drop-outside.md":"7dbd3a60","example_sortable_simple.md":"a79e26c5","example_sortable_stress-test.md":"96d71874","guide_backend_html5.md":"4fbd6b1d","guide_backend_test.md":"db434538","guide_backend_touch.md":"20fa1a9d","guide_components_dnd-provider.md":"347fbd9c","guide_components_drag-preview-image.md":"01156b20","guide_composition_index.md":"11299830","guide_composition_use-drag-layer.md":"ca65e816","guide_composition_use-drag.md":"2d17195e","guide_composition_use-drop.md":"cedc554a","guide_faq.md":"3b4eb025","guide_index.md":"11054a1a","guide_monitors_drag-layer-monitor.md":"ad37c891","guide_monitors_drag-source-monitor.md":"df9d7787","guide_monitors_drop-target-monitor.md":"d23ed319","guide_overview.md":"933c1e6f","guide_v1-to-v2.md":"74d1f773","guide_vue2.md":"e3e12ab2","index.md":"08396c98"}
