{"en_example_customize_drop-effects.md":"6cff2bab","en_example_customize_handles-and-previews.md":"b9c2e7a5","en_example_drag-around_custom-drag-layer.md":"1eafdaaf","en_example_drag-around_naive.md":"9ae27230","en_example_dustbin_copy-or-move.md":"c0c17067","en_example_dustbin_iframe.md":"3f2cfc70","en_example_dustbin_multiple-targets.md":"c6099ede","en_example_dustbin_single-target.md":"18ab93f0","en_example_dustbin_stress-test.md":"a96b220b","en_example_index.md":"eeee0ffc","en_example_nesting_drag-sources.md":"1d7ea930","en_example_nesting_drop-targets.md":"692945c8","en_example_other_native-files.md":"919f1fe9","en_example_other_native-html.md":"b11ce613","en_example_sortable_cancel-on-drop-outside.md":"8fce87bb","en_example_sortable_indicator.md":"a38ab9d0","en_example_sortable_simple.md":"278480b2","en_example_sortable_stress-test.md":"b333aa71","en_guide_backend_html5.md":"79a9d3d7","en_guide_backend_test.md":"0b97ad93","en_guide_backend_touch.md":"67949a74","en_guide_components_dnd-provider.md":"a5dfbd7f","en_guide_components_drag-preview-image.md":"86dd0979","en_guide_composition_index.md":"b7b65f5d","en_guide_composition_use-drag-layer.md":"80cb0339","en_guide_composition_use-drag.md":"eb8cbf65","en_guide_composition_use-drop.md":"e85704ff","en_guide_faq.md":"f5d98598","en_guide_index.md":"20a69eac","en_guide_monitors_drag-layer-monitor.md":"960cc3e8","en_guide_monitors_drag-source-monitor.md":"89b7b3e0","en_guide_monitors_drop-target-monitor.md":"191a4460","en_guide_overview.md":"f3de9224","en_guide_v1-to-v2.md":"6436d4ac","en_guide_vue2.md":"5f384e1d","en_index.md":"b838563c","example_customize_drop-effects.md":"f7d7c7b4","example_customize_handles-and-previews.md":"f4036f2d","example_drag-around_custom-drag-layer.md":"0b0e1fe4","example_drag-around_naive.md":"3c07d3e2","example_dustbin_copy-or-move.md":"cb666d38","example_dustbin_iframe.md":"ba5e4457","example_dustbin_multiple-targets.md":"e0958df3","example_dustbin_single-target.md":"6781a205","example_dustbin_stress-test.md":"f307893a","example_index.md":"8e3057d1","example_nesting_drag-sources.md":"3d9f998e","example_nesting_drop-targets.md":"796f400c","example_other_native-files.md":"b5efa825","example_other_native-html.md":"93084605","example_sortable_cancel-on-drop-outside.md":"ee0cefea","example_sortable_indicator.md":"1efb8df3","example_sortable_simple.md":"a120793a","example_sortable_stress-test.md":"def026cd","guide_backend_html5.md":"7a19fe6f","guide_backend_test.md":"b1a1aa32","guide_backend_touch.md":"8188e5f8","guide_components_dnd-provider.md":"4ab1a08a","guide_components_drag-preview-image.md":"533121a0","guide_composition_index.md":"1a09d10b","guide_composition_use-drag-layer.md":"80912b6f","guide_composition_use-drag.md":"ca15d9ef","guide_composition_use-drop.md":"eba97f1a","guide_faq.md":"19af306f","guide_index.md":"7129d600","guide_monitors_drag-layer-monitor.md":"2fa3a9da","guide_monitors_drag-source-monitor.md":"40e2fa9a","guide_monitors_drop-target-monitor.md":"c16d225e","guide_overview.md":"329c1f48","guide_v1-to-v2.md":"282f2f10","guide_vue2.md":"c858dc09","index.md":"691acee0"}
